masint/__init__.py
masint/api/__init__.py
masint/api/async_supermassive_intelligence.py
masint/api/supermassive_intelligence.py
masint/cli/__init__.py
masint/cli/cancel.py
masint/cli/clear_queue.py
masint/cli/ls.py
masint/cli/main.py
masint/cli/plot.py
masint/cli/squeue.py
masint/cli/stats.py
masint/cli/view_logs.py
masint/cli/view_service_logs.py
masint/engines/__init__.py
masint/engines/async_cray.py
masint/engines/cray/__init__.py
masint/engines/cray/poll_for_downloads.py
masint/engines/cray/submit_slurm_job.py
masint/engines/cray/submit_training_job.py
masint/engines/cray/upload_generate.py
masint/util/__init__.py
masint/util/get_api_base.py
masint/util/make_api_url.py
scalarlm/__init__.py
scalarlm-0.998.dist-info/METADATA
scalarlm-0.998.dist-info/WHEEL
scalarlm-0.998.dist-info/entry_points.txt
scalarlm-0.998.dist-info/top_level.txt
scalarlm-0.998.dist-info/RECORD
