Metadata-Version: 2.4
Name: scalarlm
Version: 0.998
Summary: ScalarLM is a unified LLM inference and training platform
Author-email: Greg Diamos <gregory.diamos@gmail.com>
Project-URL: Homepage, https://github.com/tensorwavecloud/scalarlm
Classifier: Programming Language :: Python :: 3
Classifier: License :: OSI Approved :: Apache Software License
Classifier: Operating System :: OS Independent
Requires-Python: >=3.7
Requires-Dist: aiohttp
Requires-Dist: aiofiles
Requires-Dist: jsonlines
Requires-Dist: matplotlib
Requires-Dist: humanize
